{
  "frames": {
    "bottomBg.png": {
      "frame": {
        "x": 0,
        "y": 0,
        "w": 640,
        "h": 185
      },
      "rotated": false,
      "trimmed": false,
      "spriteSourceSize": {
        "x": 0,
        "y": 0,
        "w": 640,
        "h": 185
      },
      "sourceSize": {
        "w": 640,
        "h": 185
      },
      "pivot": {
        "x": 0.5,
        "y": 0.5
      }
    },
    "btn01.png": {
      "frame": {
        "x": 640,
        "y": 0,
        "w": 417,
        "h": 92
      },
      "rotated": false,
      "trimmed": false,
      "spriteSourceSize": {
        "x": 0,
        "y": 0,
        "w": 417,
        "h": 92
      },
      "sourceSize": {
        "w": 417,
        "h": 92
      },
      "pivot": {
        "x": 0.5,
        "y": 0.5
      }
    },
    "bar01.png": {
      "frame": {
        "x": 1057,
        "y": 0,
        "w": 239,
        "h": 92
      },
      "rotated": false,
      "trimmed": false,
      "spriteSourceSize": {
        "x": 0,
        "y": 0,
        "w": 239,
        "h": 92
      },
      "sourceSize": {
        "w": 239,
        "h": 92
      },
      "pivot": {
        "x": 0.5,
        "y": 0.5
      }
    },
    "coins value.png": {
      "frame": {
        "x": 1296,
        "y": 0,
        "w": 227,
        "h": 35
      },
      "rotated": false,
      "trimmed": true,
      "spriteSourceSize": {
        "x": 0,
        "y": 1,
        "w": 227,
        "h": 35
      },
      "sourceSize": {
        "w": 227,
        "h": 36
      },
      "pivot": {
        "x": 0.5,
        "y": 0.5
      }
    },
    "btn02.png": {
      "frame": {
        "x": 1523,
        "y": 0,
        "w": 207,
        "h": 97
      },
      "rotated": false,
      "trimmed": false,
      "spriteSourceSize": {
        "x": 0,
        "y": 0,
        "w": 207,
        "h": 97
      },
      "sourceSize": {
        "w": 207,
        "h": 97
      },
      "pivot": {
        "x": 0.5,
        "y": 0.5
      }
    },
    "btn03.png": {
      "frame": {
        "x": 1296,
        "y": 35,
        "w": 207,
        "h": 97
      },
      "rotated": false,
      "trimmed": false,
      "spriteSourceSize": {
        "x": 0,
        "y": 0,
        "w": 207,
        "h": 97
      },
      "sourceSize": {
        "w": 207,
        "h": 97
      },
      "pivot": {
        "x": 0.5,
        "y": 0.5
      }
    },
    "coins.png": {
      "frame": {
        "x": 1730,
        "y": 0,
        "w": 109,
        "h": 35
      },
      "rotated": false,
      "trimmed": true,
      "spriteSourceSize": {
        "x": 0,
        "y": 1,
        "w": 109,
        "h": 35
      },
      "sourceSize": {
        "w": 109,
        "h": 36
      },
      "pivot": {
        "x": 0.5,
        "y": 0.5
      }
    },
    "lines.png": {
      "frame": {
        "x": 1839,
        "y": 0,
        "w": 100,
        "h": 35
      },
      "rotated": false,
      "trimmed": true,
      "spriteSourceSize": {
        "x": 1,
        "y": 1,
        "w": 100,
        "h": 35
      },
      "sourceSize": {
        "w": 102,
        "h": 36
      },
      "pivot": {
        "x": 0.5,
        "y": 0.5
      }
    },
    "minus01.png": {
      "frame": {
        "x": 1939,
        "y": 0,
        "w": 90,
        "h": 80
      },
      "rotated": false,
      "trimmed": false,
      "spriteSourceSize": {
        "x": 0,
        "y": 0,
        "w": 90,
        "h": 80
      },
      "sourceSize": {
        "w": 90,
        "h": 80
      },
      "pivot": {
        "x": 0.5,
        "y": 0.5
      }
    },
    "minus02.png": {
      "frame": {
        "x": 1730,
        "y": 35,
        "w": 90,
        "h": 80
      },
      "rotated": false,
      "trimmed": false,
      "spriteSourceSize": {
        "x": 0,
        "y": 0,
        "w": 90,
        "h": 80
      },
      "sourceSize": {
        "w": 90,
        "h": 80
      },
      "pivot": {
        "x": 0.5,
        "y": 0.5
      }
    },
    "plus01.png": {
      "frame": {
        "x": 1820,
        "y": 35,
        "w": 90,
        "h": 80
      },
      "rotated": false,
      "trimmed": false,
      "spriteSourceSize": {
        "x": 0,
        "y": 0,
        "w": 90,
        "h": 80
      },
      "sourceSize": {
        "w": 90,
        "h": 80
      },
      "pivot": {
        "x": 0.5,
        "y": 0.5
      }
    },
    "plus02.png": {
      "frame": {
        "x": 1910,
        "y": 80,
        "w": 90,
        "h": 80
      },
      "rotated": false,
      "trimmed": false,
      "spriteSourceSize": {
        "x": 0,
        "y": 0,
        "w": 90,
        "h": 80
      },
      "sourceSize": {
        "w": 90,
        "h": 80
      },
      "pivot": {
        "x": 0.5,
        "y": 0.5
      }
    }
  },
  "meta": {
    "app": "http://free-tex-packer.com",
    "version": "0.6.7",
    "image": "ui_mobile01.png",
    "format": "RGBA8888",
    "size": {
      "w": 2029,
      "h": 185
    },
    "scale": 1
  }
}